digitout/__init__.py
digitout/__main__.py
digitout/app.py
digitout/config.py
digitout/engine.py
digitout/matchers.py
digitout/traversals.py
digitout/tui.py
digitout/utils.py
digitout/widgets.py
digitout-0.1.0.dist-info/WHEEL
digitout-0.1.0.dist-info/METADATA
digitout-0.1.0.dist-info/RECORD
