Metadata-Version: 2.1
Name: digitout
Version: 0.1.0
Summary: Seek data structures of your Python application.
Author: Grzegorz Krason
Author-email: grzegorz.krason@gmail.com
Requires-Python: >=3.7,<4.0
Classifier: Programming Language :: Python :: 3
Classifier: Programming Language :: Python :: 3.7
Classifier: Programming Language :: Python :: 3.8
Requires-Dist: colorama (>=0.4.3,<0.5.0)
Requires-Dist: npyscreen (>=4.10.5,<5.0.0)
Requires-Dist: od (>=1.0,<2.0)
Requires-Dist: toml (>=0.10.0,<0.11.0)
Requires-Dist: xdg (>=4.0.1,<5.0.0)
